mds_writing_serialletter-4.6.1.dist-info/DESCRIPTION.rst
mds_writing_serialletter-4.6.1.dist-info/METADATA
mds_writing_serialletter-4.6.1.dist-info/RECORD
mds_writing_serialletter-4.6.1.dist-info/WHEEL
mds_writing_serialletter-4.6.1.dist-info/entry_points.txt
mds_writing_serialletter-4.6.1.dist-info/metadata.json
mds_writing_serialletter-4.6.1.dist-info/top_level.txt
trytond/modules/writing_serialletter/README.rst
trytond/modules/writing_serialletter/__init__.py
trytond/modules/writing_serialletter/greetings.py
trytond/modules/writing_serialletter/greetings.xml
trytond/modules/writing_serialletter/groups.xml
trytond/modules/writing_serialletter/icons.xml
trytond/modules/writing_serialletter/menu.xml
trytond/modules/writing_serialletter/party.py
trytond/modules/writing_serialletter/party.xml
trytond/modules/writing_serialletter/reportletter.py
trytond/modules/writing_serialletter/reportletter.xml
trytond/modules/writing_serialletter/salutes.py
trytond/modules/writing_serialletter/salutes.xml
trytond/modules/writing_serialletter/serialletter.py
trytond/modules/writing_serialletter/serialletter.xml
trytond/modules/writing_serialletter/tryton.cfg
trytond/modules/writing_serialletter/user.py
trytond/modules/writing_serialletter/user.xml
trytond/modules/writing_serialletter/icon/mail-reply-all.svg
trytond/modules/writing_serialletter/icon/tryton-crm.svg
trytond/modules/writing_serialletter/locale/de.po
trytond/modules/writing_serialletter/locale/de_DE.po
trytond/modules/writing_serialletter/report/serialletter.odt
trytond/modules/writing_serialletter/view/address_form.xml
trytond/modules/writing_serialletter/view/address_tree.xml
trytond/modules/writing_serialletter/view/greetings_form.xml
trytond/modules/writing_serialletter/view/greetings_tree.xml
trytond/modules/writing_serialletter/view/letter_form.xml
trytond/modules/writing_serialletter/view/letter_tree.xml
trytond/modules/writing_serialletter/view/party_form.xml
trytond/modules/writing_serialletter/view/party_tree.xml
trytond/modules/writing_serialletter/view/salutes_form.xml
trytond/modules/writing_serialletter/view/salutes_tree.xml
trytond/modules/writing_serialletter/view/user_form.xml
