Metadata-Version: 2.0
Name: mds-writing-serialletter
Version: 4.6.1
Summary: Tryton module to write serial letters for paper-based newsletters
Home-page: https://www.m-ds.de/
Author: m-ds GmbH
Author-email: service@m-ds.de
License: GPL-3
Keywords: tryton party
Platform: UNKNOWN
Classifier: Development Status :: 5 - Production/Stable
Classifier: Environment :: Plugins
Classifier: Framework :: Tryton
Classifier: Intended Audience :: Developers
Classifier: Intended Audience :: Customer Service
Classifier: Intended Audience :: Information Technology
Classifier: Intended Audience :: Financial and Insurance Industry
Classifier: Intended Audience :: Legal Industry
Classifier: Topic :: Office/Business
Classifier: Natural Language :: German
Classifier: Natural Language :: English
Classifier: Operating System :: OS Independent
Classifier: License :: OSI Approved :: GNU General Public License (GPL)
Classifier: Programming Language :: Python :: 2.7
Classifier: Programming Language :: Python :: 3.4
Classifier: Programming Language :: Python :: 3.5
Classifier: Programming Language :: Python :: 3.6
Requires-Dist: trytond-party (<4.7,>=4.6)
Requires-Dist: trytond-company (<4.7,>=4.6)
Requires-Dist: mds-party-fieldaddon (>=4.6.1)
Requires-Dist: trytond (<4.7,>=4.6)
